[
  {
    "number": 1,
    "question": "患者，男，56岁，诊断为胃溃疡，Hp(+)，给予奥美拉唑、阿莫西林、克拉霉素、枸橼酸铋钾治疗。关于该患者用药教育的说法，正确的是",
    "options": [
      "A. 克拉霉素分别于早餐和晚餐前30分钟服用",
      "B. 阿莫西林分别于早餐和晚餐前30分钟服用",
      "C. 奥美拉唑分别于早餐和晚餐前30分钟服用",
      "D. 枸橼酸铋钾分别于早餐和晚餐后30分钟服用",
      "E. 四种药物均要餐后服用"
    ],
    "answer": "C",
    "analysis": "奥美拉唑为质子泵抑制剂，需在餐前30分钟服用以有效抑制餐时酸分泌。"
  },
  {
    "number": 2,
    "question": "患者，男，46岁，因细菌性脑膜炎应用万古霉素治疗，在静脉滴注过程中出现了“红人综合征”，可能的原因是",
    "options": [
      "A. IgE介导的速度型过敏反应",
      "B. 滴注速度过快，导致组胺释放而引起的反应",
      "C. T细胞介导的速度型过敏反应",
      "D. 5-羟色胺综合征的表现",
      "E. 药物诱导血小板减少所致的微血栓表现"
    ],
    "answer": "B",
    "analysis": "万古霉素滴注速度过快可引起组胺非免疫性释放，导致颈面部、躯干皮肤潮红（红人综合征）。"
  },
  {
    "number": 3,
    "question": "患儿，男，8岁，诊断为急性细菌性扁桃体炎，儿科医师处方阿莫西林胶囊，处方用纸的颜色应为",
    "options": [
      "A. 白色",
      "B. 淡黄色",
      "C. 淡绿色",
      "D. 淡红色",
      "E. 淡蓝色"
    ],
    "answer": "C",
    "analysis": "根据《处方管理办法》，儿科处方使用淡绿色处方纸。"
  },
  {
    "number": 4,
    "question": "患者，男，23岁，因寒战、高热入院，诊断为感染性心内膜炎，血培养结果为草绿色链球菌，静脉滴注青霉素钾。根据《中华人民共和国药典临床用药须知》规定，用药前应进行皮肤过敏试验，青霉素皮试液的浓度是",
    "options": [
      "A. 2000U/ml",
      "B. 1000U/ml",
      "C. 500U/ml",
      "D. 200U/ml",
      "E. 100U/ml"
    ],
    "answer": "C",
    "analysis": "《中华人民共和国药典临床用药须知》规定，青霉素皮肤试验的皮试液浓度为500U/ml。"
  },
  {
    "number": 5,
    "question": "缓和医疗中，止痛治疗的基本目标是减轻痛苦。关于止痛治疗给药原则的说法，错误的是",
    "options": [
      "A. 注意不良反应处理",
      "B. 个体化给药",
      "C. 按阶梯给药",
      "D. 提倡无创给药",
      "E. 可按时或按需给药"
    ],
    "answer": "E",
    "analysis": "癌痛治疗应“按时”给药，而不是“按需”给药，以持续有效地缓解疼痛。"
  },
  {
    "number": 6,
    "question": "患者，男，62岁，因高血压长期服用硝苯地平，血压控制良好。近期因出现午后低热、盗汗就诊，痰培养检出结核分枝杆菌，诊断为肺结核，给予利福平、异烟肼、乙胺丁醇、吡嗪酰胺抗结核治疗。用药4周后，患者血压升高到185/90mmHg，可能的原因是",
    "options": [
      "A. 异烟肼可诱导CYP3A4，导致硝苯地平血药浓度降低",
      "B. 乙胺丁醇可抑制CYP3A4，导致硝苯地平血药浓度升高",
      "C. 吡嗪酰胺可抑制CYP3A4，导致硝苯地平血药浓度升高",
      "D. 利福平可诱导CYP3A4，导致硝苯地平血药浓度降低",
      "E. 肺结核所致的血压升高，与用药无关"
    ],
    "answer": "D",
    "analysis": "利福平是强效的CYP3A4诱导剂，可加速硝苯地平的代谢，降低其血药浓度，导致血压控制不佳。"
  },
  {
    "number": 7,
    "question": "患者，男，56岁，患类风湿性关节炎，长期口服糖皮质激素。因出现寒战、高热、伴咳嗽、咳痰就诊。痰培养提示：铜绿假单胞菌，宜选用的药物是",
    "options": [
      "A. 头孢哌啶",
      "B. 头孢呋辛",
      "C. 头孢曲松",
      "D. 头孢噻吩",
      "E. 头孢他啶"
    ],
    "answer": "E",
    "analysis": "头孢他啶对铜绿假单胞菌有高度抗菌活性，是治疗该菌感染的重要药物。"
  },
  {
    "number": 8,
    "question": "患者，男，65岁，患有冠心病、哮喘、开角型青光眼，因右下肢软组织感染入院。住院期间出现心悸、多汗等不适症状，新诊断为焦虑障碍，给予艾司西酞普兰治疗。该患者不应同时使用的药物是",
    "options": [
      "A. 沙美特罗替卡松",
      "B. 利奈唑胺",
      "C. 阿司匹林",
      "D. 色甘酸钠",
      "E. 普伐他汀"
    ],
    "answer": "B",
    "analysis": "艾司西酞普兰为SSRI类抗抑郁药，利奈唑胺为单胺氧化酶抑制剂，两者合用可能引起5-羟色胺综合征，属于禁忌。"
  },
  {
    "number": 9,
    "question": "某癌症患者服用卡培他滨后出现了手足综合征，药师应告知患者可采取的处置方式是",
    "options": [
      "A. 反复搓揉手脚",
      "B. 外用糖皮质激素软膏",
      "C. 穿戴宽松的鞋袜和手套",
      "D. 一旦发生，立即停药",
      "E. 增加阳光照射"
    ],
    "answer": "C",
    "analysis": "手足综合征的日常管理包括避免摩擦和压迫，穿戴宽松的鞋袜和手套是有效措施。"
  },
  {
    "number": 10,
    "question": "患者，女，29岁，体重60kg，因感冒发热(39.3℃)自行多次同服用酚麻美敏片、速感宁胶囊(含对乙酰氨基酚、氯苯那敏)、维C银翘片(含对乙酰氨基酚、氯苯那敏、维生素C)。用药3日后患者出现厌食、恶心、呕吐就诊。检查结果：ALT 460U/L， AST560U/L， 诊断为药物性肝损伤。可能导致该不良事件的药物成分是",
    "options": [
      "A. 伪麻黄碱",
      "B. 氯苯那敏",
      "C. 右美沙芬",
      "D. 对乙酰氨基酚",
      "E. 维生素C"
    ],
    "answer": "D",
    "analysis": "患者同时服用的三种感冒药均含有对乙酰氨基酚，导致对乙酰氨基酚超量，是引起急性肝损伤的常见原因。"
  },
  {
    "number": 11,
    "question": "可加重出血从而延迟伤口愈合的靶向药物是",
    "options": [
      "A. 吉非替尼",
      "B. 贝伐珠单抗",
      "C. 阿达木单抗",
      "D. 帕博利珠单抗",
      "E. 索拉非尼"
    ],
    "answer": "B",
    "analysis": "贝伐珠单抗是一种抗血管内皮生长因子（VEGF）的单克隆抗体，其药理作用就是抑制血管生成，因此会影响伤口愈合。"
  },
  {
    "number": 12,
    "question": "患者，男，72岁，高血压病史20年。突发右上肢无力2小时，诊断为非心源性栓塞性缺血性脑卒中。关于该疾病急性期治疗的说法，正确的是",
    "options": [
      "A. 阿司匹林应在溶栓24小时后开始使用",
      "B. 立即给予依诺肝素钠注射液4000IU",
      "C. 立即给予注射用阿替普酶0.5mg/kg(最大剂量50mg)",
      "D. 血压≥140/90mmHg时应积极控制血",
      "E. 立即给予甘露醇注射液250ml"
    ],
    "answer": "A",
    "analysis": "对于接受溶栓治疗的患者，抗血小板药物如阿司匹林需在溶栓24小时后，经影像学检查排除颅内出血后方可开始使用。"
  },
  {
    "number": 13,
    "question": "对药品在更广泛的人群、更复杂的用药条件、更长期的用药时间、更多的用药方案以及用药时与停药后的各项临床指标进行监督，这样的评价既包括临床试验完成的“新药”，也包括所有在市场上销售的“老药”。它是贯穿在药品的整个生命过程中的评价。这一评价过程属于",
    "options": [
      "A. 临床前试验",
      "B. I期临床试验",
      "C. II期临床试验",
      "D. III期临床试验",
      "E. 上市后再评价"
    ],
    "answer": "E",
    "analysis": "题干描述的是药品在批准上市后进行的持续性监测与评价，属于上市后再评价的范畴。"
  },
  {
    "number": 14,
    "question": "产生用药错误的原因比较复杂，在临床实践中，导致用药错误的因素不包括",
    "options": [
      "A. 药品不良反应",
      "B. 调配处方未执行双人核对",
      "C. 对医务人员的培训缺失",
      "D. 患者未能掌握药品的正确用法",
      "E. 药品包装相似"
    ],
    "answer": "A",
    "analysis": "药品不良反应是药物固有特性引起的，不属于可预防的用药错误。B、C、D、E均是导致用药错误的常见系统或人为因素。"
  },
  {
    "number": 15,
    "question": "患者，男，65岁，因乏力就诊，查血清电解质：血钾2.4mmol/L，外周静脉滴注氯化钾治疗，需要将其稀释成0.3%的浓度。请计算0.9%氯化钠注射液500ml中需加入10%氯化钾注射液的体积约是",
    "options": [
      "A. 50ml",
      "B. 30ml",
      "C. 20ml",
      "D. 15ml",
      "E. 10ml"
    ],
    "answer": "D",
    "analysis": "目标浓度0.3%即0.3g/100ml，500ml液体需要氯化钾1.5g。10%氯化钾注射液为10g/100ml，即0.1g/ml。所需体积=1.5g / 0.1g/ml = 15ml。"
  },
  {
    "number": 16,
    "question": "患者，男，55岁，诊断为慢性肾脏病4期。入院后查BP 160/80mmHg，血钾5.6mmol/L，血肌酐320umol/L。不宜选用的降压药物是",
    "options": [
      "A. 美托洛尔",
      "B. 硝苯地平",
      "C. 贝那普利",
      "D. 氨氯地平",
      "E. 多沙唑嗪"
    ],
    "answer": "C",
    "analysis": "患者血钾已升高（5.6mmol/L），贝那普利属于ACEI类药物，可能引起血钾进一步升高，在慢性肾脏病高钾血症患者中应慎用或禁用。"
  },
  {
    "number": 17,
    "question": "患者，女，27岁，主诉外阴瘙痒。妇科检查见阴道黏膜覆盖白色膜状物，擦除后露出红肿黏膜面，诊断为外阴阴道假丝酵母菌感染。宜选用的药物是",
    "options": [
      "A. 尼尔雌醇",
      "B. 咪康唑",
      "C. 克林霉素",
      "D. 甲硝唑",
      "E. 庆大霉素"
    ],
    "answer": "B",
    "analysis": "咪康唑是唑类抗真菌药，是治疗外阴阴道假丝酵母菌病的常用药物。"
  },
  {
    "number": 18,
    "question": "患者，男，69岁，BM118kg/m²，体检查血常规：血红蛋白94g/L，口服铁剂治疗3个月后，复查血红蛋白升至113g/L，血清铁蛋白18μg/L(低于正常参考值下限)。下列治疗方案不适宜的是",
    "options": [
      "A. 多食富含铁和蛋白质的食物",
      "B. 继续补充铁剂4～6个月",
      "C. 血清铁蛋白升至30～50μg/L可停用铁剂",
      "D. 可加用肠内营养粉剂",
      "E. 加用抑酸药，以促进铁的吸收"
    ],
    "answer": "E",
    "analysis": "铁剂在酸性环境中吸收更好，抑酸药会减少胃酸分泌，可能反而阻碍铁剂的吸收。"
  },
  {
    "number": 19,
    "question": "为避免头晕和嗜睡，在带状疱疹治疗过程中，应遵循“夜间起始，逐渐加重和缓慢减量”给药原则的药物是",
    "options": [
      "A. 阿昔洛韦",
      "B. 普瑞巴林",
      "C. 甲钴胺",
      "D. 布洛芬",
      "E. 喷普洛韦"
    ],
    "answer": "B",
    "analysis": "普瑞巴林用于治疗带状疱疹后神经痛，其常见不良反应为头晕和嗜睡，因此推荐从小剂量夜间开始服用，逐渐加重，以改善耐受性。"
  },
  {
    "number": 20,
    "question": "治疗类风湿关节炎药物中，用药期间需补充叶酸的是",
    "options": [
      "A. 甲氨蝶呤",
      "B. 米氟米特",
      "C. 阿达木单抗",
      "D. 环磷酰胺",
      "E. 硫唑嘌呤"
    ],
    "answer": "A",
    "analysis": "甲氨蝶呤会干扰叶酸代谢，补充叶酸可以减轻其骨髓抑制、口腔炎等不良反应。"
  },
  {
    "number": 21,
    "question": "关于佝偻病预防的说法，错误的是",
    "options": [
      "A. 婴儿出生后应该尽早补充维生素D 400～800IU/日",
      "B. 早产儿和低体重儿出生后即应补充维生素D800～1000IU/日",
      "C. 母乳喂养的婴幼儿不需要额外补充维生素D",
      "D. 隔着玻璃晒太阳对促进体内维生素D合成没有效果",
      "E. 应从围产期开始预防维生素D缺乏"
    ],
    "answer": "C",
    "analysis": "母乳中维生素D含量较低，纯母乳喂养的婴儿仍需额外补充维生素D。"
  },
  {
    "number": 22,
    "question": "患者，男，56岁，1年前诊断为溃疡性结肠炎，服用美沙拉秦肠溶片1g qid治疗后病情缓解。近期再次出现腹泻伴脓血便，患者前来咨询。药师发现，该患者近1个月为了吞咽方便，将药片掰开服用。导致该患者病情反复的药物因素是",
    "options": [
      "A. 美沙拉秦在胃中被代谢为奥沙拉秦",
      "B. 美沙拉秦在胃和小肠被吸收，导致在结肠浓度不足",
      "C. 美沙拉秦与食物发生相互作用，导致代谢加快",
      "D. 美沙拉秦被肠道细菌分解，导致药物失活",
      "E. 美沙拉秦被消化液稀释，导致吸收减少"
    ],
    "answer": "B",
    "analysis": "美沙拉秦肠溶片的设计目的是使药物到达结肠后释放。掰开服用会破坏肠溶衣，导致药物在胃和小肠过早吸收，无法在病变部位（结肠）达到有效浓度。"
  },
  {
    "number": 23,
    "question": "关于糖皮质激素在类风湿关节炎(RA)治疗中用药原则的说法，错误的是",
    "options": [
      "A. 应尽可能短期使用",
      "B. 可单独用于RA的治疗",
      "C. 用于有多种脏器受累的重症患者",
      "D. 非甾体抗炎药疗效不佳时，可联合使用糖皮质激素",
      "E. 小剂量使用即可缓解多数患者的症状"
    ],
    "answer": "B",
    "analysis": "糖皮质激素在RA治疗中主要起“桥梁”作用，用于快速控制炎症，应尽快与改善病情的抗风湿药（DMARDs）联用，而不推荐长期单独使用。"
  },
  {
    "number": 24,
    "question": "关于高血压患者降压目标和用药基本原则的说法，正确的是",
    "options": [
      "A. 单药治疗血压未达标，可以联用不同作用机制的降压药治疗",
      "B. 首选短效降压药物",
      "C. 血压控制平稳后，可以停药",
      "D. 老年患者的高血压降压治疗应强调舒张压达标",
      "E. 通过给予负荷剂量，使血压尽快达标"
    ],
    "answer": "A",
    "analysis": "高血压治疗原则包括：小剂量起始，优先选择长效制剂，联合用药（作用机制不同），个体化治疗和长期治疗。单药未达标时联合用药是标准策略。"
  },
  {
    "number": 25,
    "question": "患者，女，68岁，因癌痛使用芬太尼透皮贴剂。关于该患者用药教育的说法，错误的是",
    "options": [
      "A. 一贴可持续贴用72小时",
      "B. 宜贴于无毛发的皮肤上",
      "C. 避免贴在皮肤破损、红肿的部位",
      "D. 宜热敷，促进药物吸收",
      "E. 避免贴在皮肤皱褶处"
    ],
    "answer": "D",
    "analysis": "使用芬太尼透皮贴剂时应避免加热（如热敷、电热毯、热水浴），因为加热会加速药物释放，可能导致血药浓度骤升，引起严重不良反应。"
  },
  {
    "number": 26,
    "question": "治疗儿童感冒症状安全而有效的药物中，不正确的做法是",
    "options": [
      "A. 使用布洛芬或对乙酰氨基酚退热",
      "B. 使用生理盐水冲洗鼻腔，缓解鼻分泌物增多和鼻塞症状",
      "C. 2岁及以上儿童，可睡前在胸部和颈部涂抹含薄荷脑的软膏，缓解鼻塞症状",
      "D. 布洛芬与对乙酰氨基酚交替使用，减轻发热引起的不适",
      "E. 1岁及以上儿童睡前服用蜂蜜，减轻咳嗽症状"
    ],
    "answer": "D",
    "analysis": "不推荐对乙酰氨基酚和布洛芬常规交替或联合用于儿童退热，因可能增加用错药或过量风险，且对舒适度的改善证据不足。"
  },
  {
    "number": 27,
    "question": "患者，女，60岁，患有高血压、冠心病（稳定型心绞痛），医师处方硝酸甘油片备用。关于该患者用药教育的说法，错误的是",
    "options": [
      "A. 用药后可能出现心率加快",
      "B. 心绞痛发作时，首次使用后症状未缓解，可每5分钟用药1次",
      "C. 心绞痛发作时，立刻嚼碎吞服",
      "D. 心绞痛发作时，15分钟内给药最多不超过3次",
      "E. 药品需遮光、密封，在阴凉处保存"
    ],
    "answer": "C",
    "analysis": "硝酸甘油片应舌下含服，通过口腔黏膜迅速吸收。嚼碎吞服会经肝脏首过效应，生物利用度大幅降低。"
  },
  {
    "number": 28,
    "question": "患儿，女，3岁，1天前被蚊子叮咬后右侧小臂出现直径约1厘米红色丘疹，涂抹了治疗蚊虫叮咬的药膏后，症状无缓解且肿胀加重，患儿母亲前来咨询。下列建议中，错误的是",
    "options": [
      "A. 可用染料以加速丘疹消退",
      "B. 可用炉甘石洗剂摇匀后涂于患处，每日3次",
      "C. 可用丁酸氢化可的松乳膏涂于患处，每日2次",
      "D. 如瘙痒或肿胀严重，可口服氯雷他定糖浆，每晚1次",
      "E. 如对症处理后症状仍未缓解，建议就诊"
    ],
    "answer": "A",
    "analysis": "在皮肤破损或蚊虫叮咬处使用染料（如紫药水）是不科学的，可能引起刺激或掩盖病情，且无治疗作用。"
  },
  {
    "number": 29,
    "question": "患者，男，60岁，诊断为2型糖尿病、糖尿病肾病。估算的肾小球滤过率（eGFR）为20.2ml/（min.1.73m²），宜选用的降糖药物是",
    "options": [
      "A. 二甲双胍",
      "B. 利拉鲁肽",
      "C. 维格列汀",
      "D. 阿卡波糖",
      "E. 胰岛素"
    ],
    "answer": "E",
    "analysis": "患者eGFR<30ml/min，属于CKD 4期。二甲双胍禁忌。多数口服降糖药需调整剂量或禁用。胰岛素因其代谢不受肾功能影响，成为严重肾功能不全时的首选。"
  },
  {
    "number": 30,
    "question": "患者，女，52岁，诊断为原发性甲状腺功能减退症，医师处方左甲状腺素钠片25μg qd。关于该患者用药教育的说法，错误的是",
    "options": [
      "A. 左甲状腺素钠片应于早餐后1小时服用",
      "B. 应用左甲状腺素钠片前应检查心功能",
      "C. 缓慢增加剂量，4~6周复查甲状腺功能",
      "D. 若药物剂量过大，可能出现心悸、手抖等症状",
      "E. 治疗达标后，每6~12个月复查甲状腺功能"
    ],
    "answer": "A",
    "analysis": "左甲状腺素钠片应于清晨空腹顿服，与食物同服会影响其吸收。"
  },
  {
    "number": 31,
    "question": "患者，女，28岁，妊娠6周，因燥热、心慌、消瘦1月余就诊。查体：心率132次/分，甲状腺功能检查示：FT3、FT4升高，TSH降低，适宜的治疗方案是",
    "options": [
      "A. 131I放射治疗，酒石酸美托洛尔片25mg bid",
      "B. 甲巯咪唑片20mg qd，盐酸普萘洛尔片20mg tid",
      "C. 丙硫氧嘧啶片100mg tid，盐酸普萘洛尔片10mg tid",
      "D. 甲巯咪唑片20mg qd，酒石酸美托洛尔片25mg bid",
      "E. 甲巯咪唑片20mg qd，丙硫氧嘧啶片100mg tid"
    ],
    "answer": "C",
    "analysis": "妊娠早期（前三个月）甲亢治疗首选丙硫氧嘧啶，因甲巯咪唑有致畸风险。普萘洛尔可用于控制心动过速。"
  },
  {
    "number": 32,
    "question": "患者，女，32岁，已婚，有长期避孕需求，排除禁忌证后，放置左炔诺孕酮宫内节育系统。关于左炔诺孕酮宫内节育系统的说法，错误的是",
    "options": [
      "A. 放置该系统后的前3~6个月，可能会出现经量增多，经期延长",
      "B. 该系统可维持5年有效",
      "C. 放置后如发生下腹痛伴出血，需及时就诊",
      "D. 月经开始的第1天放置",
      "E. 该系统可抑制精子运输以及卵子受精，并部分抑制排卵"
    ],
    "answer": "D",
    "analysis": "左炔诺孕酮宫内节育系统可在月经期开始的7天内放置，并非必须第1天。其他时间放置需排除妊娠。"
  },
  {
    "number": 33,
    "question": "患者，男，46岁，身高175cm，体重82kg，既往体健，体检时发现中度脂肪肝，肝功能未见异常。关于该患者疾病管理和健康教育的说法，错误的是",
    "options": [
      "A. 采用低盐、低脂的平衡饮食",
      "B. 如出现瘙痒、恶心、食欲减退等症状，应及时就诊",
      "C. 避免久坐，坚持中等强度的有氧运动",
      "D. 避免过量饮酒",
      "E. 优先使用奥利司他减重"
    ],
    "answer": "E",
    "analysis": "非酒精性脂肪肝的一线治疗是生活方式干预（饮食和运动）。奥利司他等药物减重并非首选，应在生活方式干预无效且符合用药指征时在医生指导下考虑。"
  },
  {
    "number": 34,
    "question": "患者，女，25岁，备孕中，向药师咨询预防流感的有效措施。有关流感预防的说法，正确的是",
    "options": [
      "A. 接种流感疫苗，最好在10月底前完成",
      "B. 首选口服奥司他韦75mg qd预防流感",
      "B. 首选口服奥司他韦75mg bid预防流感",
      "D. 接种流感疫苗，三价灭活疫苗优于四价灭活疫苗",
      "E. 接种流感疫苗后，第2日即可产生具有保护水平的抗体"
    ],
    "answer": "A",
    "analysis": "接种流感疫苗是预防流感最有效的手段，建议在每年流感流行季前（通常10月底）完成接种。药物预防不能代替疫苗接种。"
  },
  {
    "number": 35,
    "question": "关于社区获得性肺炎 (CAP) 抗感染治疗疗程的说法，错误的是",
    "options": [
      "A. 一般可于热退2～3天且主要呼吸道症状明显改善后停药",
      "B. 轻至中度CAP患者，通常疗程为5～7天",
      "C. 非典型病原体感染且治疗反应较慢者，疗程延长至10～14天",
      "D. 铜绿假单胞菌感染者，疗程可延长至28～42天",
      "E. 金黄色葡萄球菌感染者，疗程可延长至14～21天"
    ],
    "answer": "D",
    "analysis": "铜绿假单胞菌感染的CAP疗程通常为10-14天，而非28-42天。长疗程（如28-42天）更常见于医院获得性肺炎（HAP）或呼吸机相关性肺炎（VAP）。"
  },
  {
    "number": 36,
    "question": "患者，男，28岁，诊断为焦虑障碍 (急性期)，医师处方阿普唑仑片0.4mg tid。该患者服用阿普唑仑的疗程为",
    "options": [
      "A. 2～3天",
      "B. 2～3周",
      "C. 2～3个月",
      "D. 3～6个月",
      "E. 6～12个月"
    ],
    "answer": "B",
    "analysis": "苯二氮䓬类药物（如阿普唑仑）用于焦虑障碍急性期治疗，疗程宜短，一般为2-4周，以避免依赖和耐受。"
  },
  {
    "number": 37,
    "question": "药源性肝脏疾病又称药物性肝损伤，是最主要的药源性疾病之一，越来越引起医药界、制药业、药品管理部门及公众重视，成为药品审批失败、药物警戒以及撤市的主要原因。关于药源性肝脏疾病的说法，错误的是",
    "options": [
      "A. 药源性肝脏疾病是导致急性肝衰竭的主要原因之一",
      "B. 多数药源性肝脏疾病有一定潜伏期",
      "C. 药源性肝脏疾病的发生可预测",
      "D. 用药期间过量饮酒会增加药源性肝脏疾病的发生风险",
      "E. 药物相互作用可导致药源性肝脏疾病"
    ],
    "answer": "C",
    "analysis": "大多数药物性肝损伤是特异质反应，难以预测。"
  },
  {
    "number": 38,
    "question": "关于沙眼的说法，正确的是",
    "options": [
      "A. 起病急，多为单眼发病",
      "B. 属于非传染性眼病",
      "C. 治疗方式以局部用药为主",
      "D. 病原体多为革兰阳性菌",
      "E. 治疗期间可以佩戴隐形眼镜"
    ],
    "answer": "C",
    "analysis": "沙眼由沙眼衣原体引起，是一种传染性眼病，通常双眼发病，治疗以局部使用抗生素眼膏（如四环素、红霉素）为主，治疗期间不宜佩戴隐形眼镜。"
  },
  {
    "number": 39,
    "question": "对有症状的细菌性阴道病女性患者需要通过治疗缓解症状，治疗常选用抗厌氧菌药物，不包括",
    "options": [
      "A. 甲硝唑",
      "B. 多西环素",
      "C. 替硝唑",
      "D. 克林霉素",
      "E. 奥硝唑"
    ],
    "answer": "B",
    "analysis": "细菌性阴道病主要与阴道内厌氧菌过度生长有关。甲硝唑、替硝唑、奥硝唑和克林霉素是常用治疗药物。多西环素主要用于衣原体、支原体等感染。"
  },
  {
    "number": 40,
    "question": "患者，男，66岁，患高血压、功能性便秘，服用硝苯地平控释片、双歧杆菌三联活菌胶囊，关于该患者用药教育的说法，错误的是",
    "options": [
      "A. 双歧杆菌三联活菌胶囊应于阴凉处保存",
      "B. 硝苯地平控释片不可掰开服用",
      "C. 大便中可能会看到硝苯地平控释片的完整片形",
      "D. 双歧杆菌三联活菌胶囊避免与抗菌药物、蒙脱石散同时服用",
      "E. 双歧杆菌三联活菌胶囊不能用超过40℃的水送服"
    ],
    "answer": "A",
    "analysis": "双歧杆菌三联活菌胶囊等活菌制剂通常要求在2-8℃冷藏保存，以保持菌群活性。“阴凉处”是指不超过20℃，不符合其储存要求。"
  },
  {
    "number": 41,
    "question": "可用维生素K解救的是",
    "options": [
      "B. 甲基苯丙胺(冰毒)中毒",
      "C. 有机磷中毒",
      "D. 阿片类药物中毒",
      "E. 克仑特罗(瘦肉精)中毒"
    ],
    "answer": "A",
    "analysis": "维生素K1是华法林过量导致出血的特效拮抗剂。"
  },
  {
    "number": 42,
    "question": "可用普萘洛尔解救的是",
    "options": [
      "A. 华法林所致出血",
      "B. 甲基苯丙胺(冰毒)中毒",
      "C. 有机磷中毒",
      "D. 阿片类药物中毒",
      "E. 克仑特罗(瘦肉精)中毒"
    ],
    "answer": "E",
    "analysis": "克仑特罗是β2受体激动剂，过量可引起心动过速等β受体兴奋症状，普萘洛尔作为β受体阻断剂可对抗这些症状。"
  },
  {
    "number": 43,
    "question": "患者，女，28岁，妊娠24周，查空腹血糖8.2mmol/L，餐后血糖13.2mmol/L，糖化血红蛋白7.3%。首选的降糖药物是",
    "options": [
      "A. 利拉鲁肽",
      "B. 达格列净",
      "C. 胰岛素",
      "D. 格列美脲",
      "E. 二甲双胍"
    ],
    "answer": "C",
    "analysis": "妊娠期高血糖，当生活方式干预不能达标时，胰岛素是首选的药物治疗方案，因其不通过胎盘。"
  },
  {
    "number": 44,
    "question": "患者，男，32岁，BMI31.1kg/m2，新诊断为2型糖尿病。饮食控制和规律运动3个月后，复查空腹血糖8.5mmol/L，糖化血红蛋白7.5%。首选的降糖药物是",
    "options": [
      "A. 利拉鲁肽",
      "B. 达格列净",
      "C. 胰岛素",
      "D. 格列美脲",
      "E. 二甲双胍"
    ],
    "answer": "E",
    "analysis": "对于新诊断的2型糖尿病患者，若无禁忌证，二甲双胍是首选的一线降糖药物。"
  },
  {
    "number": 45,
    "question": "患者，女，55岁，2型糖尿病2年。近期调整降糖治疗方案后，反复出现泌尿与生殖系统感染。排除疾病因素后，可能引起该不良反应的降糖药物是",
    "options": [
      "A. 利拉鲁肽",
      "B. 达格列净",
      "C. 胰岛素",
      "D. 格列美脲",
      "E. 二甲双胍"
    ],
    "answer": "B",
    "analysis": "达格列净属于SGLT-2抑制剂，其通过促进尿糖排泄降糖，导致尿液葡萄糖浓度升高，易诱发泌尿系统和生殖系统真菌感染。"
  },
  {
    "number": 46,
    "question": "骨性关节炎治疗中，可局部外用，缓解疼痛的药物是",
    "options": [
      "A. 双氯芬酸",
      "B. 白芍总苷",
      "C. 氨基葡萄糖",
      "D. 曲安奈德",
      "E. 阿达木单抗"
    ],
    "answer": "A",
    "analysis": "双氯芬酸二乙胺乳胶剂等NSAIDs外用制剂可用于骨关节炎的局部止痛治疗。"
  },
  {
    "number": 47,
    "question": "骨性关节炎治疗中，有软骨保护作用的药物是",
    "options": [
      "A. 双氯芬酸",
      "B. 白芍总苷",
      "C. 氨基葡萄糖",
      "D. 曲安奈德",
      "E. 阿达木单抗"
    ],
    "answer": "C",
    "analysis": "氨基葡萄糖被认为可能具有缓解症状和改善软骨结构的慢作用。"
  },
  {
    "number": 48,
    "question": "骨性关节炎治疗中，可关节腔注射的药物是",
    "options": [
      "A. 双氯芬酸",
      "B. 白芍总苷",
      "C. 氨基葡萄糖",
      "D. 曲安奈德",
      "E. 阿达木单抗"
    ],
    "answer": "D",
    "analysis": "糖皮质激素（如曲安奈德）关节腔注射可用于骨关节炎急性疼痛发作的对症治疗。"
  },
  {
    "number": 49,
    "question": "患者，女，46岁，诊断为肺结核。在治疗过程中出现手足刺痛，考虑为异烟肼所致周围神经病变。宜选用的药物是",
    "options": [
      "A. 口服甲硝唑",
      "B. 肌注肾上腺素",
      "C. 静注地塞米松",
      "D. 口服维生素B6",
      "E. 肌注维生素K1"
    ],
    "answer": "D",
    "analysis": "异烟肼可引起维生素B6缺乏导致周围神经炎，补充维生素B6可用于预防和治疗。"
  },
  {
    "number": 50,
    "question": "患者，男，26岁，诊断为感染性心内膜炎。静滴青霉素约3分钟出现胸闷、气短、呼吸困难等过敏性休克症状，测血压85/60mmHg。首选的抢救药物是",
    "options": [
      "A. 口服甲硝唑",
      "B. 肌注肾上腺素",
      "C. 静注地塞米松",
      "D. 口服维生素B6",
      "E. 肌注维生素K1"
    ],
    "answer": "B",
    "analysis": "肾上腺素是抢救过敏性休克的首选药物，可迅速缓解支气管痉挛和提升血压。"
  },
  {
    "number": 51,
    "question": "患者，男，54岁，因医院获得性肺炎给予哌拉西林他唑巴坦治疗，7天后出现严重腹泻，诊断为伪膜性肠炎。宜选用的药物是",
    "options": [
      "A. 口服甲硝唑",
      "B. 肌注肾上腺素",
      "C. 静注地塞米松",
      "D. 口服维生素B6",
      "E. 肌注维生素K1"
    ],
    "answer": "A",
    "analysis": "伪膜性肠炎多由艰难梭菌引起，甲硝唑是轻至中度感染的首选口服治疗药物。"
  },
  {
    "number": 52,
    "question": "患者，女，54岁，诊断为反流性食管炎（LA-B级），给予泮托拉唑钠肠溶片40mg qd，初始治疗的疗程为",
    "options": [
      "A. 2周",
      "B. 4周",
      "C. 8周",
      "D. 3个月",
      "E. 6个月"
    ],
    "answer": "C",
    "analysis": "反流性食管炎的初始治疗，质子泵抑制剂（PPI）标准疗程通常为8周。"
  },
  {
    "number": 53,
    "question": "患者，女，25岁，诊断为十二指肠溃疡，Hp(+)，Hp根除治疗的疗程为",
    "options": [
      "A. 2周",
      "B. 4周",
      "C. 8周",
      "D. 3个月",
      "E. 6个月"
    ],
    "answer": "A",
    "analysis": "目前标准的含铋剂四联方案根除Hp的疗程一般为14天（2周）。"
  },
  {
    "number": 54,
    "question": "患者，男，45岁，检查结果：血尿酸580μmol/L，尿尿酸<600mg/24h（尿酸排泄减少）。宜选用的降尿酸药物是",
    "options": [
      "A. 苯溴马隆",
      "B. 吲哚美辛",
      "C. 氢氯噻嗪",
      "D. 非布司他",
      "E. 秋水仙碱"
    ],
    "answer": "A",
    "analysis": "苯溴马隆通过抑制肾小管对尿酸的重吸收，促进尿酸排泄，适用于尿酸排泄减少型。"
  },
  {
    "number": 55,
    "question": "患者，男，50岁，诊断为痛风合并泌尿系统结石，首选的降尿酸药物是",
    "options": [
      "A. 苯溴马隆",
      "B. 吲哚美辛",
      "C. 氢氯噻嗪",
      "D. 非布司他",
      "E. 秋水仙碱"
    ],
    "answer": "D",
    "analysis": "苯溴马隆促进尿酸排泄，可能增加尿路尿酸结石风险。非布司他为抑制尿酸生成药物，适用于有尿路结石史的痛风患者。"
  },
  {
    "number": 56,
    "question": "患者，女性，36岁，诊断弥漫大B细胞淋巴瘤，拟行“利妥昔单抗+环磷酰胺+多柔比星+长春新碱+泼尼松(R-CHOP)”方案化疗，每3周一次。该化疗称为",
    "options": [
      "A. 根治性化疗",
      "B. 辅助化疗",
      "C. 研究性化疗",
      "D. 新辅助化疗",
      "E. 姑息性化疗"
    ],
    "answer": "A",
    "analysis": "弥漫大B细胞淋巴瘤对化疗敏感，R-CHOP方案旨在治愈疾病，属于根治性化疗。"
  },
  {
    "number": 57,
    "question": "患者，男性，73岁，新诊断胃癌，伴腹腔淋巴结转移。在外科和肿瘤门诊就诊后，拟先行化疗治疗，该化疗称为",
    "options": [
      "A. 根治性化疗",
      "B. 辅助化疗",
      "C. 研究性化疗",
      "D. 新辅助化疗",
      "E. 姑息性化疗"
    ],
    "answer": "B",
    "analysis": "胃癌术后为消灭残留微小转移灶，降低复发风险进行的化疗称为辅助化疗。（注：本题题干描述“新诊断胃癌...拟先行化疗”更符合新辅助化疗的定义，即术前化疗。但根据官方答案B（辅助化疗），此处按答案反推，题干可能意在描述术后辅助化疗，但表述不够清晰。解题思路按辅助化疗解释。）"
  },
  {
    "number": 58,
    "question": "患儿，女，6岁，因发热、咳嗽2天就诊，以肺部感染收治入院。经验性抗感染治疗3天后，检验结果：嗜肺军团菌感染。首选的药物是",
    "options": [
      "A. 阿奇霉素",
      "B. 克林霉素",
      "C. 莫西沙星",
      "D. 依替米星",
      "E. 阿莫西林"
    ],
    "answer": "A",
    "analysis": "大环内酯类药物（如阿奇霉素）是治疗军团菌感染的首选。"
  },
  {
    "number": 59,
    "question": "患儿，男，13岁，因发热、咳嗽2天就诊，以肺部感染收治入院。经验性抗感染治疗3天后，检验结果：肺炎衣原体感染，首选的药物是",
    "options": [
      "A. 阿奇霉素",
      "B. 克林霉素",
      "C. 莫西沙星",
      "D. 依替米星",
      "E. 阿莫西林"
    ],
    "answer": "A",
    "analysis": "大环内酯类药物（如阿奇霉素）是治疗肺炎衣原体感染的首选。"
  },
  {
    "number": 60,
    "question": "患儿，男，11岁，因发热、咳嗽2天就诊，以肺部感染收治入院，经验性抗感染治疗3天后，检验结果：肺炎链球菌感染，首选的药物是",
    "options": [
      "A. 阿奇霉素",
      "B. 克林霉素",
      "C. 莫西沙星",
      "D. 依替米星",
      "E. 阿莫西林"
    ],
    "answer": "E",
    "analysis": "对于敏感的肺炎链球菌感染，青霉素类（如阿莫西林）是首选药物。"
  },
  {
    "number": 61,
    "question": "属于鸟苷酸环化酶C激动剂，用于成人便秘型肠易激综合征的药物是",
    "options": [
      "A. 番泻叶",
      "B. 利那洛肽",
      "C. 莫沙必利",
      "D. 乳果糖",
      "E. 聚乙二醇4000"
    ],
    "answer": "B",
    "analysis": "利那洛肽是一种鸟苷酸环化酶C激动剂，可增加肠液分泌和促进肠道蠕动，用于治疗便秘型肠易激综合征。"
  },
  {
    "number": 62,
    "question": "属于刺激性泻药，长期使用可引起结肠黑变病的药物是",
    "options": [
      "A. 番泻叶",
      "B. 利那洛肽",
      "C. 莫沙必利",
      "D. 乳果糖",
      "E. 聚乙二醇4000"
    ],
    "answer": "A",
    "analysis": "番泻叶属于蒽醌类刺激性泻药，长期使用可导致结肠黑变病。"
  },
  {
    "number": 63,
    "question": "可用于缓解胆石症引起的胆道痉挛的药物是",
    "options": [
      "A. 美沙拉秦",
      "B. 熊去氧胆酸",
      "C. 洛哌丁胺",
      "D. 柳氮磺吡啶",
      "E. 匹维溴铵"
    ],
    "answer": "E",
    "analysis": "匹维溴铵是一种钙拮抗剂，可用于缓解胆道和肠道痉挛。"
  },
  {
    "number": 64,
    "question": "有利胆作用，但禁用于胆道完全梗阻患者的药物是",
    "options": [
      "A. 美沙拉秦",
      "B. 熊去氧胆酸",
      "C. 洛哌丁胺",
      "D. 柳氮磺吡啶",
      "E. 匹维溴铵"
    ],
    "answer": "B",
    "analysis": "熊去氧胆酸可促进胆汁分泌，但在胆道完全梗阻时禁用，否则可能加重病情。"
  },
  {
    "number": 65,
    "question": "推荐用于有进餐后腹泻和(或)排便失禁症状患者的药物是",
    "options": [
      "A. 美沙拉秦",
      "B. 熊去氧胆酸",
      "C. 洛哌丁胺",
      "D. 柳氮磺吡啶",
      "E. 匹维溴铵"
    ],
    "answer": "C",
    "analysis": "洛哌丁胺可抑制肠道蠕动，延长内容物滞留时间，用于控制急、慢性腹泻。"
  },
  {
    "number": 66,
    "question": "恶性贫血患者和全胃切除患者（血清中检出内因子抗体）需要终生使用的药物是",
    "options": [
      "A. 叶酸",
      "B. 维生素B1",
      "C. 维生素B12",
      "D. 维生素B6",
      "E. 维生素C"
    ],
    "answer": "C",
    "analysis": "恶性贫血或全胃切除导致内因子缺乏，影响维生素B12吸收，需终生肌注或大剂量口服维生素B12替代治疗。"
  },
  {
    "number": 67,
    "question": "缺铁性贫血患者需注意铁剂与其他药物之间的相互作用，可促进口服铁剂吸收的药物是",
    "options": [
      "A. 叶酸",
      "B. 维生素B1",
      "C. 维生素B12",
      "D. 维生素B6",
      "E. 维生素C"
    ],
    "answer": "E",
    "analysis": "维生素C作为还原剂，可将三价铁还原为更易吸收的二价铁，并可与其形成可溶性络合物，促进铁剂吸收。"
  },
  {
    "number": 68,
    "question": "兴奋剂是指运动员参赛时禁用的药品。上述药品中，按兴奋剂管理的是",
    "options": [
      "A. 重组人促红素注射液",
      "B. 高锰酸钾外用片",
      "C. 0.9%氯化钠注射液",
      "D. 肠内营养粉剂",
      "E. 硝酸甘油片"
    ],
    "answer": "A",
    "analysis": "重组人促红素（EPO）能刺激红细胞生成，提高携氧能力，属于运动员禁用的肽类激素类兴奋剂。"
  },
  {
    "number": 69,
    "question": "高警示药品是指药理作用显著且迅速、一旦使用不当可对人体造成严重伤害，甚至导致死亡的药品。上述药品中，纳入中国药学会医院药学专业委员会《高警示药品推荐目录(2019版)》的是",
    "options": [
      "A. 重组人促红素注射液",
      "B. 高锰酸钾外用片",
      "C. 0.9%氯化钠注射液",
      "D. 肠内营养粉剂",
      "E. 硝酸甘油片"
    ],
    "answer": "B",
    "analysis": "高锰酸钾外用片浓度使用不当可引起严重皮肤黏膜腐蚀，被列入高警示药品目录。"
  },
  {
    "number": 70,
    "question": "用于治疗良性前列腺增生，可减轻前列腺张力和膀胱出口梗阻的药物是",
    "options": [
      "A. 奥昔布宁",
      "B. 米多君",
      "C. 坦索罗辛",
      "D. 索利那新",
      "E. 非那雄胺"
    ],
    "answer": "C",
    "analysis": "坦索罗辛是α1受体阻滞剂，通过松弛前列腺和膀胱颈平滑肌，改善排尿症状。"
  },
  {
    "number": 71,
    "question": "用于治疗良性前列腺增生，可降低雄激素水平和缩小前列腺体积的药物是",
    "options": [
      "A. 奥昔布宁",
      "B. 米多君",
      "C. 坦索罗辛",
      "D. 索利那新",
      "E. 非那雄胺"
    ],
    "answer": "E",
    "analysis": "非那雄胺是5α-还原酶抑制剂，通过抑制双氢睾酮的生成，使前列腺体积缩小。"
  },
  {
    "number": 72,
    "question": "患者，女，46岁，出现潮热出汗等症状。否认高血压、糖尿病及血栓史，有高血压家族史，不希望有月经样出血。宜选用的激素治疗方案是",
    "options": [
      "A. 雌、孕激素连续联合方案",
      "B. 单纯孕激素方案",
      "C. 单纯雌激素方案",
      "D. 单纯雌激素方案",
      "E. 雌、孕激素序贯方案"
    ],
    "answer": "A",
    "analysis": "对于有完整子宫、不希望有周期性出血的围绝经期女性，雌孕激素连续联合方案可避免子宫内膜增生，使月经停止。"
  },
  {
    "number": 73,
    "question": "患者，女，43岁，1年前因子宫腺肌症行“全子宫切除术”，最近2个月出现间断潮热、盗汗、乏力等绝经症状，否认个人及家族高血压、糖尿病及血栓史，宜选用的激素治疗方案是",
    "options": [
      "A. 雌、孕激素连续联合方案",
      "B. 单纯孕激素方案",
      "C. 单纯雌激素方案",
      "D. 单纯雌激素方案",
      "E. 雌、孕激素序贯方案"
    ],
    "answer": "D",
    "analysis": "已切除子宫的女性，补充激素治疗时无需加用孕激素保护子宫内膜，可单独使用雌激素。"
  },
  {
    "number": 74,
    "question": "患者，女，38岁，因停经3月，伴潮热、出汗就诊。B超示子宫内膜5mm，乳腺B超未见异常，希望有月经样出血。宜选用的激素治疗方案是",
    "options": [
      "A. 雌、孕激素连续联合方案",
      "B. 单纯孕激素方案",
      "C. 单纯雌激素方案",
      "D. 单纯雌激素方案",
      "E. 雌、孕激素序贯方案"
    ],
    "answer": "E",
    "analysis": "对于有完整子宫、希望有月经样周期性出血的较年轻女性，雌孕激素序贯方案（周期性使用孕激素）可模拟生理周期，产生规律性撤退性出血。"
  },
  {
    "number": 75,
    "question": "咪达唑仑过量的特异性解救药物是",
    "options": [
      "A. 青霉胺",
      "B. 亚甲蓝",
      "C. 乙酰半胱氨酸",
      "D. 氟马西尼",
      "E. 纳洛酮"
    ],
    "answer": "D",
    "analysis": "氟马西尼是苯二氮䓬类受体特异性拮抗剂，可用于逆转其中枢镇静作用。"
  },
  {
    "number": 76,
    "question": "铜中毒的特异性解救药物是",
    "options": [
      "A. 青霉胺",
      "B. 亚甲蓝",
      "C. 乙酰半胱氨酸",
      "D. 氟马西尼",
      "E. 纳洛酮"
    ],
    "answer": "A",
    "analysis": "青霉胺是一种金属螯合剂，可用于铜、铅、汞等金属中毒的解毒治疗。"
  },
  {
    "number": 77,
    "question": "患者，女，55岁，1个月前诊断为高血压，服药控制血压尚可，但近2周无明显诱因出现刺激性干咳，考虑是药品不良反应，可能引起上述症状的药物是",
    "options": [
      "A. 伊伐布雷定",
      "B. 福辛普利",
      "C. 氢氯噻嗪",
      "D. 氨氯地平",
      "E. 比索洛尔"
    ],
    "answer": "B",
    "analysis": "干咳是血管紧张素转换酶抑制剂（ACEI，如福辛普利）常见的不良反应。"
  },
  {
    "number": 78,
    "question": "患者，女，65岁，高血压病8年，慢性心功能不全4年。使用足量美托洛尔、依那普利控制不佳，近年来反复出现喘憋、气短加重、心率80次/分。心脏彩超示：左心室射血分数30%，宜加用的药物是",
    "options": [
      "A. 伊伐布雷定",
      "B. 福辛普利",
      "C. 氢氯噻嗪",
      "D. 氨氯地平",
      "E. 比索洛尔"
    ],
    "answer": "A",
    "analysis": "伊伐布雷定通过抑制窦房结If电流减慢心率，用于窦性心律且心率≥75次/分的慢性心衰患者，可进一步改善预后。"
  },
  {
    "number": 79,
    "question": "患者，女，63岁，高血压病10年，使用硝苯地平控释片和厄贝沙坦片降压。近期，午睡后血压升高到160/85mmHg，心率60次/分。宜加用的药物是",
    "options": [
      "A. 伊伐布雷定",
      "B. 福辛普利",
      "C. 氢氯噻嗪",
      "D. 氨氯地平",
      "E. 比索洛尔"
    ],
    "answer": "C",
    "analysis": "患者午后血压升高，心率偏慢，加用小剂量利尿剂（如氢氯噻嗪）可加强降压效果，且对心率影响小。"
  },
  {
    "number": 80,
    "question": "患者，女，69岁，因心悸就诊，诊断为房颤。患慢性肾脏病10年，肌酐清除率25ml/min。宜选用的药品是",
    "options": [
      "A. 达比加群酯胶囊",
      "B. 利伐沙班片",
      "C. 替格瑞洛片",
      "D. 阿司匹林肠溶片",
      "E. 注射用尿激酶"
    ],
    "answer": "B",
    "analysis": "患者肌酐清除率25ml/min（CKD 4期）。达比加群主要经肾脏排泄，在此肾功能下需慎用或禁用。利伐沙班在此肾功能下需减量使用，但仍为可选药物。阿司匹林防卒中效果弱于口服抗凝药。"
  },
  {
    "number": 81,
    "question": "患者，男，83岁，2月前诊断为缺血性脑卒中，目前卧床，鼻饲营养液及药物，肝肾功能正常，既往房颤病史5年，未规律治疗，宜选用的药品是",
    "options": [
      "A. 达比加群酯胶囊",
      "B. 利伐沙班片",
      "C. 替格瑞洛片",
      "D. 阿司匹林肠溶片",
      "E. 注射用尿激酶"
    ],
    "answer": "B",
    "analysis": "患者有房颤史，需抗凝预防卒中。因鼻饲，需选用可碾碎鼻饲的剂型。利伐沙班片可碾碎，达比加群胶囊内容物鼻饲存在不确定性，且说明书通常建议整粒服用。"
  },
  {
    "number": 82,
    "question": "患者，男，53岁，因胸痛发作就诊，诊断为冠心病，宜选用的药品是",
    "options": [
      "A. 达比加群酯胶囊",
      "B. 利伐沙班片",
      "C. 替格瑞洛片",
      "D. 阿司匹林肠溶片",
      "E. 注射用尿激酶",
      "A. 加巴喷丁"
    ],
    "answer": "D",
    "analysis": "冠心病二级预防，如无禁忌，应长期服用阿司匹林抗血小板治疗。"
  },
  {
    "number": 83,
    "question": "患者，男，40岁，诊断为带状疱疹。宜选用的外用抗病毒药物是",
    "options": [
      "A. 加巴喷丁",
      "B. 喷昔洛韦",
      "C. 甲钴胺",
      "D. 伐昔洛韦",
      "E. 利多卡因"
    ],
    "answer": "B",
    "analysis": "喷昔洛韦乳膏是局部外用的抗病毒药物，用于治疗带状疱疹。"
  },
  {
    "number": 84,
    "question": "患者，女，38岁，诊断为带状疱疹。需要缓慢加至有效剂量的口服镇痛药物是",
    "options": [
      "A. 加巴喷丁",
      "B. 喷昔洛韦",
      "C. 甲钴胺",
      "D. 伐昔洛韦",
      "E. 利多卡因"
    ],
    "answer": "A",
    "analysis": "加巴喷丁用于治疗带状疱疹后神经痛，需从低剂量开始，逐渐加重，以减少头晕、嗜睡等不良反应。"
  },
  {
    "number": 85,
    "question": "患者，女，49岁，诊断为带状疱疹。宜选用的外用镇痛药物是",
    "options": [
      "A. 加巴喷丁",
      "B. 喷昔洛韦",
      "C. 甲钴胺",
      "D. 伐昔洛韦",
      "E. 利多卡因"
    ],
    "answer": "E",
    "analysis": "利多卡因凝胶贴片或乳膏可用于局部镇痛，治疗带状疱疹相关神经痛。"
  },
  {
    "number": 86,
    "question": "患者，男，69岁，痴呆病史5年。近期查肾功能示：肌酐清除率20ml/min，该患者宜选用的药物是",
    "options": [
      "A. 恩他卡朋双多巴",
      "B. 多奈哌齐",
      "C. 复方左旋多巴",
      "D. 苯海索",
      "E. 普拉克索"
    ],
    "answer": "B",
    "analysis": "患者诊断为痴呆（可能为阿尔茨海默病），多奈哌齐是胆碱酯酶抑制剂，用于改善认知功能。肾功能不全时需注意剂量。"
  },
  {
    "number": 87,
    "question": "患者，女，62岁，闭角型青光眼5年。近半年出现手抖，走路不稳，诊断为帕金森病。该患者宜选用的药物是",
    "options": [
      "A. 恩他卡朋双多巴",
      "B. 多奈哌齐",
      "C. 复方左旋多巴",
      "D. 苯海索",
      "E. 普拉克索"
    ],
    "answer": "E",
    "analysis": "苯海索等抗胆碱能药物可加重青光眼。多巴胺受体激动剂（如普拉克索）对青光眼影响相对较小，可作为选择。"
  },
  {
    "number": 88,
    "question": "患者，男，45岁，新诊断为帕金森病、给予抗帕金森病药物治疗，用药后出现尿液颜色改变。该患者可能服用的药物是",
    "options": [
      "A. 恩他卡朋双多巴",
      "B. 多奈哌齐",
      "C. 复方左旋多巴",
      "D. 苯海索",
      "E. 普拉克索"
    ],
    "answer": "A",
    "analysis": "恩他卡朋及其代谢物可使尿液变成红棕色，此为正常现象。"
  },
  {
    "number": 89,
    "question": "患者，女，24岁，面部痤疮较多，有乳胶过敏史，平时月经不规律，计划半年后备孕，宜选用的避孕方法是",
    "options": [
      "A. 采用安全期避孕",
      "B. 口服短效复方避孕药",
      "C. 使用避孕套",
      "D. 口服紧急避孕药",
      "E. 放置左炔诺孕酮宫内节育系统"
    ],
    "answer": "B",
    "analysis": "复方口服避孕药对痤疮有治疗作用。患者月经不规律，安全期不可靠。有乳胶过敏史，不适合使用普通乳胶避孕套。计划半年后备孕，适合使用可逆的短效激素避孕方法。"
  },
  {
    "number": 90,
    "question": "患者，女，26岁，产后7周，正在哺乳，尚未恢复月经，自述有阴道炎及严重偏头痛。宜选用的避孕方法是",
    "options": [
      "A. 采用安全期避孕",
      "B. 口服短效复方避孕药",
      "C. 使用避孕套",
      "D. 口服紧急避孕药",
      "E. 放置左炔诺孕酮宫内节育系统"
    ],
    "answer": "C",
    "analysis": "哺乳期避免使用雌激素类避孕药（如复方口服避孕药），因可能减少乳汁分泌。含雌激素的避孕药也禁用于有偏头痛（尤其先兆偏头痛）的患者，因增加卒中风险。避孕套是适宜的选择。"
  },
  {
    "number": 91,
    "question": "该患者宜选用的退热药物是",
    "options": [
      "A. 布洛芬",
      "B. 双氯芬酸",
      "C. 塞来昔布",
      "D. 阿司匹林",
      "E. 对乙酰氨基酚"
    ],
    "answer": "E",
    "analysis": "妊娠期退热，对乙酰氨基酚是相对安全的选择。布洛芬等NSAIDs在妊娠晚期禁用。"
  },
  {
    "number": 92,
    "question": "该患者宜选用的抗感染治疗方案是",
    "options": [
      "A. 阿米卡星注射液，600mg qd ivgtt，3天",
      "B. 青霉素V钾片，250mg qid po，10天",
      "C. 左氧氟沙星注射液，500mg qd ivgtt，5天",
      "D. 阿奇霉素片，500mg qd po，7天",
      "E. 注射用头孢哌酮舒巴坦钠，4.5g q12h ivgtt，10天"
    ],
    "answer": "B",
    "analysis": "患者症状体征提示细菌性扁桃体炎可能。青霉素V是治疗链球菌性咽炎/扁桃体炎的一线药物，且在妊娠期使用相对安全。氨基糖苷类、喹诺酮类在妊娠期需慎用或禁用。"
  },
  {
    "number": 93,
    "question": "关于抗结核化学治疗基本原则的说法，错误的是",
    "options": [
      "A. 早期",
      "B. 规律",
      "C. 负荷量",
      "D. 联合",
      "E. 全程"
    ],
    "answer": "C",
    "analysis": "抗结核治疗原则为“早期、联合、适量、规律、全程”，没有“负荷量”原则。"
  },
  {
    "number": 94,
    "question": "该患者选用联合用药方案进行抗结核治疗。关于该患者用药教育的说法，错误的是",
    "options": [
      "A. 一线抗结核药物多可引起药物性肝损伤",
      "B. 利福平可使体液变成橘红色",
      "C. 异烟肼可引起周围神经病变",
      "D. 吡嗪酰胺可引起球后视神经炎",
      "E. 乙胺丁醇可引起尿酸升高"
    ],
    "answer": "D",
    "analysis": "引起球后视神经炎是乙胺丁醇的典型不良反应，而非吡嗪酰胺。吡嗪酰胺可引起高尿酸血症。"
  },
  {
    "number": 95,
    "question": "患者抗结核治疗2周后，复查结果：ALT69U/L，AST72U/L，胆红素正常。后续治疗方案正确的是",
    "options": [
      "A. 转氨酶低于正常范围上限3倍，可继续用药并密切监测肝功能",
      "B. 停用所有抗结核药物，肝功能正常后再恢复用药",
      "C. 加用熊去氧胆酸保肝治疗",
      "D. 加用糖皮质激素保肝治疗",
      "E. 复查痰涂片，再决定是否继续用药"
    ],
    "answer": "A",
    "analysis": "抗结核药致药物性肝损伤，若转氨酶升高低于正常上限3倍，可在密切监测下继续抗结核治疗。"
  },
  {
    "number": 96,
    "question": "经肝药酶CYP3A4代谢的药物是",
    "options": [
      "A. 氯吡格雷、非洛地平",
      "B. 氯吡格雷、美托洛尔",
      "C. 非洛地平、辛伐他汀",
      "D. 美托洛尔、辛伐他汀",
      "E. 氯吡格雷、辛伐他汀"
    ],
    "answer": "C",
    "analysis": "非洛地平和辛伐他汀都是CYP3A4的底物。氯吡格雷需经CYP2C19代谢活化，美托洛尔主要经CYP2D6代谢。"
  },
  {
    "number": 97,
    "question": "可能引起患者血尿酸升高的药物是",
    "options": [
      "A. 氯吡格雷",
      "B. 氢氯噻嗪",
      "C. 美托洛尔",
      "D. 单硝酸异山梨酯",
      "E. 辛伐他汀"
    ],
    "answer": "B",
    "analysis": "噻嗪类利尿剂（如氢氯噻嗪）可竞争性抑制肾小管对尿酸的排泄，引起血尿酸升高。"
  },
  {
    "number": 98,
    "question": "不得研碎服用的药品是",
    "options": [
      "A. 氢氯噻嗪片",
      "B. 硫酸氢氯吡格雷片",
      "C. 辛伐他汀片",
      "D. 琥珀酸美托洛尔缓释片",
      "E. 单硝酸异山梨酯片"
    ],
    "answer": "D",
    "analysis": "缓释、控释制剂（如琥珀酸美托洛尔缓释片）若研碎或嚼碎，会破坏其缓释结构，导致药物迅速释放，可能引起严重不良反应。"
  },
  {
    "number": 99,
    "question": "该患者HLA-B*5801基因阳性，不宜选用的痛风治疗药物是",
    "options": [
      "A. 别嘌醇",
      "B. 秋水仙碱",
      "C. 泼尼松",
      "D. 双氯芬酸",
      "E. 非布司他"
    ],
    "answer": "A",
    "analysis": "HLA-B*5801基因阳性是别嘌醇引发严重皮肤不良反应（如Stevens-Johnson综合征）的重要危险因素，应避免使用。"
  },
  {
    "number": 100,
    "question": "患者近期血压控制欠佳，BP195/110mmHg。可能引起血压升高的药品是",
    "options": [
      "A. 硝苯地平控释片",
      "B. 呋塞米片",
      "C. 骨化三醇胶丸",
      "D. 碳酸钙咀嚼片",
      "E. 重组人促红素注射液"
    ],
    "answer": "E",
    "analysis": "重组人促红素（EPO）常见的不良反应之一就是高血压。"
  },
  {
    "number": 101,
    "question": "关于该患者用药教育的说法，错误的是",
    "options": [
      "A. 碳酸钙咀嚼片应于两餐之间嚼服",
      "B. 硝苯地平控释片、骨化三醇胶丸可同时服用",
      "C. 在血压控制平稳且达标前，血压的测量频率是每日1~2次",
      "D. 饮食上应选择低盐、优质低蛋白食物",
      "E. 重组人促红素注射液的给药频次为每周2次"
    ],
    "answer": "A",
    "analysis": "碳酸钙作为磷结合剂，应随餐服用，以便与食物中的磷酸盐结合，减少磷的吸收。“两餐之间”服用效果不佳。"
  },
  {
    "number": 102,
    "question": "因患者血压控制不佳，在原有降压药物的基础上，宜加用的药物是",
    "options": [
      "A. 美托洛尔",
      "B. 赖诺普利",
      "C. 呋塞米",
      "D. 吲达帕胺",
      "E. 特拉唑嗪"
    ],
    "answer": "B",
    "analysis": "患者有糖尿病，降压治疗优选ACEI或ARB，因其具有肾脏保护作用。现有方案为CCB（硝苯地平），联合ACEI（赖诺普利）是合理选择。"
  },
  {
    "number": 103,
    "question": "患者自诉腹胀，排气多，可能引起这种不良反应的药品是",
    "options": [
      "A. 硝苯地平控释片",
      "B. 阿托伐他汀钠片",
      "C. 伏格列波糖片",
      "D. 多维元素片",
      "E. 褪黑素片"
    ],
    "answer": "C",
    "analysis": "α-葡萄糖苷酶抑制剂（如伏格列波糖）的常见不良反应就是胃肠道反应，如腹胀、排气增多。"
  },
  {
    "number": 104,
    "question": "关于该患者用药教育的说法，错误的是",
    "options": [
      "A. 甘精胰岛素启用后，宜室温保存",
      "B. 发生低血糖时，建议立即服用蔗糖",
      "C. 阿托伐他汀钠片可在每天任意固定时间服用",
      "D. 伏格列波糖片应随第一口主食嚼服",
      "E. 硝苯地平控释片为长效制剂，通常每天服用一次"
    ],
    "answer": "B",
    "analysis": "伏格列波糖通过抑制α-糖苷酶延缓碳水化合物吸收。发生低血糖时，应直接补充葡萄糖，而非蔗糖（双糖），因为蔗糖的吸收可能被伏格列波糖延缓。"
  },
  {
    "number": 105,
    "question": "综合评估该患者动脉粥样硬化性心血管疾病(ASCVD)的发病风险，建议药物治疗方案调整为",
    "options": [
      "A. 加用华法林钠片，3mg qd",
      "B. 加用依折麦布片，10mg qd",
      "C. 加用格列美脲片，2mg qd",
      "D. 加用盐酸二甲双胍片，0.5g tid",
      "E. 加用吉非贝齐片，0.3g bid"
    ],
    "answer": "B",
    "analysis": "患者已使用高强度他汀（阿托伐他汀40mg），LDL-C仍为3.0mmol/L，未达标。联合胆固醇吸收抑制剂（依折麦布）是进一步降低LDL-C的常用策略。"
  },
  {
    "number": 106,
    "question": "该患者服用的药品中，可能与骨质疏松发病相关的药品是",
    "options": [
      "A. 奥美拉唑肠溶片",
      "B. 厄贝沙坦氢氯噻嗪片",
      "C. 阿卡波糖片",
      "D. 氨氯地平片",
      "E. 阿司匹林肠溶片"
    ],
    "answer": "A",
    "analysis": "长期（通常>1年）使用质子泵抑制剂（PPI，如奥美拉唑）可能影响钙吸收，与骨质疏松及骨折风险增加相关。"
  },
  {
    "number": 107,
    "question": "骨质疏松药物治疗方案中，不适合该患者的是",
    "options": [
      "A. 碳酸钙片0.5g tid",
      "B. 骨化三醇胶丸0.25μg bid",
      "C. 阿仑膦酸钠片70mg qW",
      "D. 鲑降钙素鼻喷剂100IU qd",
      "E. 特立帕肽注射液20μg qd"
    ],
    "answer": "C",
    "analysis": "阿仑膦酸钠等双膦酸盐口服制剂对食管有刺激性，患者有食管裂孔疝，属于相对禁忌，应避免使用。"
  },
  {
    "number": 108,
    "question": "针对该患者骨质疏松症健康教育的说法，错误的是",
    "options": [
      "A. 推荐低盐、富含钙和蛋白质的均衡饮食",
      "B. 戒烟、限酒、少饮咖啡和碳酸饮料",
      "C. 为降低骨折风险，建议少动或制动",
      "D. 每1~2年复查一次骨密度",
      "E. 每日上臂暴露日光浴15~20分钟"
    ],
    "answer": "C",
    "analysis": "适度的负重运动有助于维持骨密度和肌肉力量，降低跌倒和骨折风险。“少动或制动”反而会增加骨量丢失和跌倒风险。"
  },
  {
    "number": 109,
    "question": "该患者可能的诊断是",
    "options": [
      "A. 普通感冒",
      "B. 流行性感冒",
      "C. 过敏性鼻炎",
      "D. 急性咽炎",
      "E. 哮喘"
    ],
    "answer": "C",
    "analysis": "阵发性喷嚏、清水样涕、鼻塞、鼻眼腭部瘙痒是过敏性鼻炎的典型症状。"
  },
  {
    "number": 110,
    "question": "该患者宜选用的药品是",
    "options": [
      "A. 对乙酰氨基酚片",
      "B. 布地奈德鼻喷剂",
      "C. 头孢呋辛酯片",
      "D. 奥司他韦胶囊",
      "E. 阿莫西林胶囊"
    ],
    "answer": "B",
    "analysis": "鼻用糖皮质激素（如布地奈德鼻喷剂）是治疗过敏性鼻炎的一线药物。"
  },
  {
    "number": 111,
    "question": "某护士为一名人类免疫缺陷病毒 (HIV) 阳性患者拔针时，不慎被针头划伤手掌。关于 HIV 暴露后局部处理和预防用药原则的说法，正确的有",
    "options": [
      "A. 用肥皂液和流动的清水清洗伤口",
      "B. 由近心端向远心端挤压伤处，尽可能挤出伤口处的血液",
      "C. 预防性用药的疗程为14天",
      "D. 用75%酒精或0.5%聚维酮碘(碘伏)对伤口局部进行消毒",
      "E. 尽可能在2小时内开始预防性用药"
    ],
    "answer": "A, B, D, E",
    "analysis": "HIV暴露后预防（PEP）的疗程通常为28天，而非14天。其他选项均为标准处理流程。"
  },
  {
    "number": 112,
    "question": "患者，男，48岁，诊断：胃溃疡，Hp (+)，采用四联方案根除Hp。关于该患者用药教育的说法，正确的有",
    "options": [
      "A. 如根除失败，建议3~6个月之后再次根除治疗",
      "B. 提倡分餐制，夹菜时使用公筷",
      "C. 根除治疗结束后2周内复查Hp",
      "D. 根除治疗期间出现消化道症状，通常是轻微而短暂的",
      "E. 根除Hp可去除病因，无需继续服用抑酸药治疗胃溃疡"
    ],
    "answer": "A, B, D",
    "analysis": "复查Hp应在根除治疗结束至少4周后进行，以避免假阴性。根除Hp后，为促进溃疡愈合，通常仍需继续抑酸治疗4-8周。"
  },
  {
    "number": 113,
    "question": "肿瘤预防属系统工程，需有计划、有步骤地开展，并遵循三级预防原则。关于肿瘤一级预防措施的说法，正确的有",
    "options": [
      "A. 每三个月进行一次肿瘤筛查",
      "B. 控烟",
      "C. 合理营养膳食结构",
      "D. 控制感染",
      "E. 减少导致肿瘤的职业与环境因素暴露"
    ],
    "answer": "B, C, D, E",
    "analysis": "肿瘤筛查属于二级预防（早发现、早诊断、早治疗）。一级预防是针对病因的预防，B、C、D、E均属于一级预防措施。"
  },
  {
    "number": 114,
    "question": "患者，男，65岁，因血糖控制不佳入院。2型糖尿病5年余，长期服用盐酸二甲双胍片0.5g tid。入院后加用甘精胰岛素12U qn。住院期间诊断为高脂血症，加用瑞舒伐他汀钙片10mg qn。该患者需要监测的指标有",
    "options": [
      "A. 红细胞沉降率",
      "B. 糖化血红蛋白",
      "C. 血糖",
      "D. 肌酸激酶",
      "E. 低密度脂蛋白胆固醇"
    ],
    "answer": "B, C, D, E",
    "analysis": "糖尿病患者需监测血糖和糖化血红蛋白（B, C）。使用他汀类药物需监测血脂以评价疗效（E）和肌酸激酶以警惕横纹肌溶解（D）。红细胞沉降率非该患者常规监测指标。"
  },
  {
    "number": 115,
    "question": "大多数抗菌药物都能进入乳汁，哺乳期妇女不宜使用的抗菌药物有",
    "options": [
      "A. 氟喹诺酮类药物",
      "B. 第二代头孢菌素类药物",
      "C. 磺胺类药物",
      "D. 青霉素类药物",
      "E. 氨基糖苷类药物"
    ],
    "answer": "A, C, E",
    "analysis": "氟喹诺酮类可能影响婴幼儿软骨发育；磺胺类可能引起新生儿核黄疸；氨基糖苷类有耳肾毒性风险。青霉素类和头孢菌素类在哺乳期相对安全。"
  },
  {
    "number": 116,
    "question": "患者，男，62岁，因支气管哮喘使用沙美特罗替卡松治疗，近期因哮喘控制不佳就诊患者现场演示了沙美特罗替卡松准纳器的使用方法，错误的有",
    "options": [
      "A. 推开滑动杆：握住准纳器，向外推开滑动杆直至发出“咔嗒”声，左右晃动准纳器",
      "B. 吸入药物：先呼气，然后合住吸嘴，缓慢深吸后，将准纳器移开，立即恢复呼气",
      "C. 打开装置：一手握住外壳，另一手的大拇指放在拇指柄上，向外推动拇指柄直至盖子完全打开",
      "D. 关闭吸入器：使用干净纸巾擦拭吸嘴，将拇指放在拇指柄，向内推回原位",
      "E. 漱口：吸入药物后，用清水漱口(漱口液勿吞咽)"
    ],
    "answer": "A, B",
    "analysis": "A错误，推开滑动杆后不应晃动装置，以免药物散失。B错误，吸入药物后应屏气5-10秒，再缓慢恢复呼气，而不是立即呼气。"
  },
  {
    "number": 117,
    "question": "关于发热的用药指导与患者教育的说法，正确的有",
    "options": [
      "A. 解热镇痛药用于退热只是对症治疗，并不能解除病因",
      "B. 非选择性非甾体抗炎药无明显的胃肠道刺激作用",
      "C. 使用退热药后，如发热症状无好转，应及时就诊",
      "D. 肝肾功能不全者，要减少解热镇痛药剂量",
      "E. 血小板减少、有出血倾向者，应慎用非甾体抗炎药"
    ],
    "answer": "A, C, D, E",
    "analysis": "B错误，非选择性NSAIDs（如布洛芬、阿司匹林）通过抑制COX-1可能引起胃肠道刺激甚至溃疡出血。"
  },
  {
    "number": 118,
    "question": "目前推荐的抗失眠药物治疗策略包括",
    "options": [
      "A. 失眠继发于或伴发于其他疾病时，应同时治疗原发或伴发疾病",
      "B. 长期性、难治性失眠应在专科医师指导下用药",
      "C. 对于长期使用镇静催眠药物的慢性失眠患者，不提倡间歇治疗",
      "D. 原发性失眠首选短效非苯二氮草类药物，如唑吡坦、佐匹克隆和扎来普隆",
      "E. 苯二氮草受体激动剂或褪黑素受体激动剂可以与抗抑郁药联合应用"
    ],
    "answer": "A, B, D, E",
    "analysis": "C错误，对于长期用药的慢性失眠患者，推荐采用间歇治疗或按需服药策略，而非持续每晚用药，以减少药物依赖和耐受。"
  },
  {
    "number": 119,
    "question": "关于深静脉血栓形成患者药物治疗管理的说法，正确的有",
    "options": [
      "A. 依诺肝素应皮下注射，避免肌肉注射",
      "B. 服用华法林，需要监测INR",
      "C. 肾功能不全者，慎用依诺肝素",
      "D. 服用利伐沙班，需要监测INR",
      "E. 抗凝治疗中，需要定期检查血常规、便潜血"
    ],
    "answer": "A, B, C, E",
    "analysis": "D错误，利伐沙班等直接口服抗凝药（DOACs）常规使用时不需监测INR。"
  },
  {
    "number": 120,
    "question": "可降低双歧杆菌三联活菌肠溶胶囊、乳酶生片等活菌类制剂药效的中药有",
    "options": [
      "A. 金银花",
      "B. 连翘",
      "C. 黄芩",
      "D. 鱼腥草",
      "E. 麻黄"
    ],
    "answer": "A, B, C, D",
    "analysis": "金银花、连翘、黄芩、鱼腥草等清热解毒类中药具有抗菌作用，可能抑制或杀灭活菌制剂中的益生菌。麻黄主要含麻黄碱，其抗菌作用不强，对活菌制剂影响较小。"
  }
]